peepingtom/__init__.py
peepingtom/__main__.py
peepingtom/_version.py
peepingtom/functions.py
peepingtom/peeper.py
peepingtom/_tests/__init__.py
peepingtom/_tests/test_cli.py
peepingtom/_tests/test_peep.py
peepingtom/_tests/test_peeper.py
peepingtom/datablocks/__init__.py
peepingtom/datablocks/abstractblocks/__init__.py
peepingtom/datablocks/abstractblocks/datablock.py
peepingtom/datablocks/abstractblocks/metablock.py
peepingtom/datablocks/abstractblocks/metamultiblock.py
peepingtom/datablocks/abstractblocks/multiblock.py
peepingtom/datablocks/abstractblocks/simpleblock.py
peepingtom/datablocks/abstractblocks/spatialblock.py
peepingtom/datablocks/abstractblocks/_tests/test_datablock.py
peepingtom/datablocks/abstractblocks/_tests/test_multiblock.py
peepingtom/datablocks/abstractblocks/_tests/test_simpleblock.py
peepingtom/datablocks/multiblocks/__init__.py
peepingtom/datablocks/multiblocks/dipoleblock.py
peepingtom/datablocks/multiblocks/meshblock.py
peepingtom/datablocks/multiblocks/orientedpointblock.py
peepingtom/datablocks/multiblocks/particleblock.py
peepingtom/datablocks/multiblocks/sphereblock.py
peepingtom/datablocks/multiblocks/transformblock.py
peepingtom/datablocks/multiblocks/_tests/__init__.py
peepingtom/datablocks/multiblocks/_tests/test_dipoleblock.py
peepingtom/datablocks/multiblocks/_tests/test_meshblock.py
peepingtom/datablocks/multiblocks/_tests/test_particleblock.py
peepingtom/datablocks/multiblocks/_tests/test_sphereblock.py
peepingtom/datablocks/multiblocks/_tests/test_transformblock.py.old
peepingtom/datablocks/simpleblocks/__init__.py
peepingtom/datablocks/simpleblocks/imageblock.py
peepingtom/datablocks/simpleblocks/lineblock.py
peepingtom/datablocks/simpleblocks/orientationblock.py
peepingtom/datablocks/simpleblocks/pointblock.py
peepingtom/datablocks/simpleblocks/propertyblock.py
peepingtom/datablocks/simpleblocks/_tests/__init__.py
peepingtom/datablocks/simpleblocks/_tests/test_imageblock.py
peepingtom-0.2.0.dist-info/LICENSE
peepingtom-0.2.0.dist-info/METADATA
peepingtom-0.2.0.dist-info/WHEEL
peepingtom-0.2.0.dist-info/entry_points.txt
peepingtom-0.2.0.dist-info/top_level.txt
peepingtom-0.2.0.dist-info/RECORD
