Metadata-Version: 2.1
Name: peepingtom
Version: 0.2.0
Summary: Python tool for visualising and interacting with cryo-ET and subtomogram averaging data.
Home-page: https://github.com/gutsche-lab/peepingtom/
Author: PeepingTom Team
Author-email: peepingtom_team@googlegroups.com
License: BSD 3-Clause
Platform: UNKNOWN
Classifier: Development Status :: 2 - Pre-Alpha
Classifier: Environment :: X11 Applications :: Qt
Classifier: Intended Audience :: Education
Classifier: Intended Audience :: Science/Research
Classifier: License :: OSI Approved :: BSD License
Classifier: Programming Language :: Python
Classifier: Programming Language :: Python :: 3 :: Only
Classifier: Programming Language :: Python :: 3.7
Classifier: Programming Language :: Python :: 3.8
Classifier: Topic :: Scientific/Engineering
Classifier: Topic :: Scientific/Engineering :: Visualization
Classifier: Topic :: Scientific/Engineering :: Information Analysis
Classifier: Topic :: Scientific/Engineering :: Bio-Informatics
Classifier: Topic :: Utilities
Classifier: Operating System :: Microsoft :: Windows
Classifier: Operating System :: POSIX
Classifier: Operating System :: Unix
Classifier: Operating System :: MacOS
Requires-Python: >=3.8
License-File: LICENSE
Requires-Dist: napari[all] (>=0.4.8)
Requires-Dist: numpy
Requires-Dist: pandas
Requires-Dist: scipy
Requires-Dist: pyqtgraph
Requires-Dist: click
Requires-Dist: dynamotable (~=0.2.4)
Requires-Dist: eulerangles (~=1.0.1)
Requires-Dist: mrcfile (~=1.3.0)
Requires-Dist: starfile (~=0.4.4)
Requires-Dist: emfile (~=0.2)
Provides-Extra: dev
Requires-Dist: pytest ; extra == 'dev'
Requires-Dist: pytest-qt ; extra == 'dev'
